topsis/__init__.py
topsis/__main__.py
Topsis_Akshat_101917081-1.0.0.dist-info/LICENSE
Topsis_Akshat_101917081-1.0.0.dist-info/METADATA
Topsis_Akshat_101917081-1.0.0.dist-info/WHEEL
Topsis_Akshat_101917081-1.0.0.dist-info/entry_points.txt
Topsis_Akshat_101917081-1.0.0.dist-info/top_level.txt
Topsis_Akshat_101917081-1.0.0.dist-info/RECORD
